spook/__init__.py
spook/base.py
spook/contraction_utils.py
spook/lin_solve.py
spook/quad_program.py
spook/utils.py
spook/vmi_special.py
spook/xval.py
fdgi-1.0.3.dist-info/LICENSE
fdgi-1.0.3.dist-info/METADATA
fdgi-1.0.3.dist-info/WHEEL
fdgi-1.0.3.dist-info/top_level.txt
fdgi-1.0.3.dist-info/RECORD
