Metadata-Version: 2.1
Name: FDGI
Version: 1.0.3
Summary: A package for spectral-domain ghost imaging
Home-page: https://github.com/congzlwag/spook
Author: Jun Wang
Author-email: junwang9@stanford.edu
Project-URL: Bug Tracker, https://github.com/congzlwag/spook/issues
Classifier: Programming Language :: Python :: 3
Classifier: License :: OSI Approved :: MIT License
Classifier: Operating System :: OS Independent
Requires-Python: >=3.7
License-File: LICENSE
Requires-Dist: numpy >=1.19
Requires-Dist: scipy >=1.7
Requires-Dist: osqp >=0.6.2
